{"stats":{"minecraft:custom":{"minecraft:time_since_rest":14115,"minecraft:crouch_one_cm":2611,"minecraft:play_time":14115,"lootr:looted_stat":20,"minecraft:sprint_one_cm":44476,"minecraft:damage_taken":198,"minecraft:walk_one_cm":33504,"minecraft:sneak_time":1678,"minecraft:bell_ring":16,"minecraft:drop":5,"minecraft:jump":82,"minecraft:damage_dealt":761,"minecraft:time_since_death":14115,"minecraft:walk_on_water_one_cm":196,"minecraft:total_world_time":14115,"minecraft:damage_resisted":0,"minecraft:interact_with_crafting_table":1,"minecraft:fall_one_cm":3106,"minecraft:fly_one_cm":20764},"minecraft:mined":{"biomesoplenty:fir_leaves":2,"lootr:trophy":1},"minecraft:dropped":{"minecraft:iron_ingot":5,"aether:leather_gloves":1,"minecraft:wheat_seeds":3},"minecraft:picked_up":{"minecraft:wheat_seeds":3,"minecraft:iron_ingot":5,"lootr:trophy":1},"minecraft:used":{"minecraft:iron_chestplate":1,"minecraft:chainmail_helmet":1,"minecraft:iron_sword":7,"minecraft:chainmail_leggings":1}},"DataVersion":3465}